serdataclasses/__init__.py
serdataclasses/deserialize.py
serdataclasses/errors.py
serdataclasses/py.typed
serdataclasses/serialize.py
serdataclasses/typedefs.py
serdataclasses-0.8.0.dist-info/LICENSE
serdataclasses-0.8.0.dist-info/WHEEL
serdataclasses-0.8.0.dist-info/METADATA
serdataclasses-0.8.0.dist-info/RECORD
