Metadata-Version: 2.1
Name: serdataclasses
Version: 0.8.0
Summary: Serialize/deserialize Python objects from/to typed structures.
Home-page: https://github.com/pappasam/serdataclasses
License: MIT
Keywords: typing,json,serde,serialize,deserialize
Author: Sam Roeca
Author-email: samuel.roeca@gmail.com
Requires-Python: >=3.8,<4.0
Classifier: Development Status :: 3 - Alpha
Classifier: License :: OSI Approved :: MIT License
Classifier: Operating System :: OS Independent
Classifier: Programming Language :: Python :: 3
Classifier: Programming Language :: Python :: 3.8
Classifier: Programming Language :: Python :: 3.9
Classifier: Topic :: Software Development :: Libraries :: Python Modules
Classifier: Topic :: Utilities
Classifier: Typing :: Typed
Project-URL: Repository, https://github.com/pappasam/serdataclasses
